krl_data_connectors/__init__.py
krl_data_connectors/__version__.py
krl_data_connectors/base_connector.py
krl_data_connectors/base_dispatcher_connector.py
krl_data_connectors/licensed_connector_mixin.py
krl_data_connectors/agricultural/__init__.py
krl_data_connectors/business/__init__.py
krl_data_connectors/civic/__init__.py
krl_data_connectors/civic/census_tiger_connector.py
krl_data_connectors/community/__init__.py
krl_data_connectors/community/bls_basic.py
krl_data_connectors/community/census_acs_public.py
krl_data_connectors/community/fred_basic.py
krl_data_connectors/community/civic/__init__.py
krl_data_connectors/community/civic/datagov_catalog.py
krl_data_connectors/community/demographic/__init__.py
krl_data_connectors/community/demographic/census_cbp_summary.py
krl_data_connectors/community/demographic/datagov_demographic.py
krl_data_connectors/community/demographic/ssa_actuarial.py
krl_data_connectors/community/economic/__init__.py
krl_data_connectors/community/economic/bea_national.py
krl_data_connectors/community/economic/datagov_economic.py
krl_data_connectors/community/economic/oecd_indicators.py
krl_data_connectors/community/education/__init__.py
krl_data_connectors/community/education/datagov_education.py
krl_data_connectors/community/education/nces_school_directory.py
krl_data_connectors/community/environmental/__init__.py
krl_data_connectors/community/environmental/datagov_environmental.py
krl_data_connectors/community/environmental/noaa_climate_current.py
krl_data_connectors/community/financial/__init__.py
krl_data_connectors/community/financial/datagov_financial.py
krl_data_connectors/community/financial/treasury_public_debt.py
krl_data_connectors/community/geographic/__init__.py
krl_data_connectors/community/geographic/datagov_geographic.py
krl_data_connectors/community/geographic/usgs_earthquakes.py
krl_data_connectors/community/health/__init__.py
krl_data_connectors/community/health/datagov_health.py
krl_data_connectors-1.0.1.dist-info/licenses/LICENSE
krl_data_connectors-1.0.1.dist-info/METADATA
krl_data_connectors-1.0.1.dist-info/WHEEL
krl_data_connectors-1.0.1.dist-info/top_level.txt
krl_data_connectors-1.0.1.dist-info/RECORD
