Metadata-Version: 2.4
Name: krl-data-connectors
Version: 1.0.1
Summary: Production-ready data connectors for 68 government and research data sources across 27 domains. Community tier (12 FREE connectors) included. Professional and Enterprise tiers available.
Author-email: KR-Labs Foundation <dev@krlabs.dev>
Maintainer-email: KR-Labs Foundation <dev@krlabs.dev>
License: Apache-2.0
Project-URL: Homepage, https://krlabs.dev
Project-URL: Documentation, https://docs.krlabs.dev/data-connectors
Project-URL: Repository, https://github.com/KR-Labs/krl-data-connectors
Project-URL: Bug Tracker, https://github.com/KR-Labs/krl-data-connectors/issues
Project-URL: Changelog, https://github.com/KR-Labs/krl-data-connectors/blob/main/CHANGELOG.md
Keywords: economics,data,api,fred,census,bls,world-bank,oecd,connectors,socioeconomic,policy-analysis
Classifier: Development Status :: 5 - Production/Stable
Classifier: Intended Audience :: Developers
Classifier: Intended Audience :: Science/Research
Classifier: License :: OSI Approved :: Apache Software License
Classifier: Operating System :: OS Independent
Classifier: Programming Language :: Python :: 3
Classifier: Programming Language :: Python :: 3.11
Classifier: Programming Language :: Python :: 3.12
Classifier: Programming Language :: Python :: 3.13
Classifier: Topic :: Scientific/Engineering
Classifier: Topic :: Software Development :: Libraries :: Python Modules
Requires-Python: >=3.11
License-File: LICENSE
Requires-Dist: requests>=2.28.0
Requires-Dist: pandas>=2.1.0
Requires-Dist: numpy>=1.26.0
Requires-Dist: krl-types~=0.2.0
Provides-Extra: enterprise
Requires-Dist: airbyte-api>=0.53.0; extra == "enterprise"
Requires-Dist: httpx>=0.25.0; extra == "enterprise"
Requires-Dist: supermemory>=0.1.0; extra == "enterprise"
Provides-Extra: ai
Requires-Dist: httpx>=0.25.0; extra == "ai"
Requires-Dist: supermemory>=0.1.0; extra == "ai"
Requires-Dist: fastapi>=0.109.0; extra == "ai"
Requires-Dist: uvicorn>=0.27.0; extra == "ai"
Requires-Dist: pydantic>=2.0.0; extra == "ai"
Provides-Extra: dev
Requires-Dist: black>=23.0.0; extra == "dev"
Requires-Dist: isort>=5.12.0; extra == "dev"
Requires-Dist: flake8>=6.0.0; extra == "dev"
Requires-Dist: mypy>=1.0.0; extra == "dev"
Requires-Dist: pre-commit>=3.0.0; extra == "dev"
Requires-Dist: ruff>=0.1.8; extra == "dev"
Provides-Extra: test
Requires-Dist: pytest>=7.2.0; extra == "test"
Requires-Dist: pytest-cov>=4.0.0; extra == "test"
Requires-Dist: pytest-xdist>=3.0.0; extra == "test"
Requires-Dist: pytest-mock>=3.10.0; extra == "test"
Requires-Dist: pytest-timeout>=2.2.0; extra == "test"
Requires-Dist: pytest-randomly>=3.15.0; extra == "test"
Requires-Dist: pytest-benchmark>=4.0.0; extra == "test"
Requires-Dist: responses>=0.23.0; extra == "test"
Requires-Dist: requests-mock>=1.11.0; extra == "test"
Requires-Dist: hypothesis>=6.92.0; extra == "test"
Provides-Extra: security
Requires-Dist: bandit[toml]>=1.7.5; extra == "security"
Requires-Dist: safety>=3.0.0; extra == "security"
Requires-Dist: pip-audit>=2.6.0; extra == "security"
Provides-Extra: performance
Requires-Dist: locust>=2.20.0; extra == "performance"
Requires-Dist: pytest-benchmark>=4.0.0; extra == "performance"
Requires-Dist: memory-profiler>=0.61.0; extra == "performance"
Provides-Extra: mutation
Requires-Dist: mutmut>=2.4.0; extra == "mutation"
Provides-Extra: e2e
Requires-Dist: playwright>=1.40.0; extra == "e2e"
Requires-Dist: pytest-playwright>=0.4.0; extra == "e2e"
Provides-Extra: contract
Requires-Dist: pydantic>=2.5.0; extra == "contract"
Requires-Dist: schemathesis>=3.27.0; extra == "contract"
Provides-Extra: docs
Requires-Dist: sphinx>=6.0.0; extra == "docs"
Requires-Dist: sphinx-rtd-theme>=1.2.0; extra == "docs"
Requires-Dist: sphinx-autodoc-typehints>=1.22.0; extra == "docs"
Provides-Extra: all
Requires-Dist: krl-data-connectors[contract,dev,docs,e2e,mutation,performance,security,test]; extra == "all"
Dynamic: license-file
